dvadmin_apscheduler/__init__.py
dvadmin_apscheduler/apps.py
dvadmin_apscheduler/models.py
dvadmin_apscheduler/settings.py
dvadmin_apscheduler/tasks.py
dvadmin_apscheduler/urls.py
dvadmin_apscheduler/fixtures/__init__.py
dvadmin_apscheduler/fixtures/init_menu.json
dvadmin_apscheduler/fixtures/initialize.py
dvadmin_apscheduler/migrations/0001_initial.py
dvadmin_apscheduler/migrations/__init__.py
dvadmin_apscheduler/views/__init__.py
dvadmin_apscheduler/views/task.py
dvadmin_apscheduler/views/task_detail.py
dvadmin_apscheduler-1.0.0.data/data/init_menu.json
dvadmin_apscheduler-1.0.0.dist-info/METADATA
dvadmin_apscheduler-1.0.0.dist-info/WHEEL
dvadmin_apscheduler-1.0.0.dist-info/top_level.txt
dvadmin_apscheduler-1.0.0.dist-info/RECORD
