Metadata-Version: 2.1
Name: dvadmin-apscheduler
Version: 1.0.0
Summary: 适用于 django-vue-admin 的apscheduler同步插件
Home-page: https://gitee.com/huge-dream/dvadmin-apscheduler
Author: DVAdmin
Author-email: liqiang@django-vue-admin.com
Classifier: Programming Language :: Python :: 3
Classifier: License :: OSI Approved :: MIT License
Classifier: Operating System :: OS Independent
Requires-Python: >=3.7, <4
Requires-Dist: django-apscheduler (>=0.6.2)
Requires-Dist: django-redis (>=5.0.0)
